sphinx_seeta_theme/__init__.py
sphinx_seeta_theme/breadcrumbs.html
sphinx_seeta_theme/footer.html
sphinx_seeta_theme/globaltoc.html
sphinx_seeta_theme/layout.html
sphinx_seeta_theme/localtoc.html
sphinx_seeta_theme/navbar.html
sphinx_seeta_theme/navbarsearchbox.html
sphinx_seeta_theme/search.html
sphinx_seeta_theme/sidebar.html
sphinx_seeta_theme/theme.conf
sphinx_seeta_theme/version.py
sphinx_seeta_theme/ext/__init__.py
sphinx_seeta_theme/ext/linkcode.py
sphinx_seeta_theme/ext/viewcode.py
sphinx_seeta_theme/static/pygments.css
sphinx_seeta_theme/static/css/bootstrap.min.css
sphinx_seeta_theme/static/css/copy_button.css
sphinx_seeta_theme/static/css/footer.css
sphinx_seeta_theme/static/css/layout1.css
sphinx_seeta_theme/static/css/layout3.css
sphinx_seeta_theme/static/css/theme.css
sphinx_seeta_theme/static/fonts/font-awesome/css/font-awesome.css
sphinx_seeta_theme/static/fonts/font-awesome/css/font-awesome.min.css
sphinx_seeta_theme/static/fonts/font-awesome/fonts/FontAwesome.otf
sphinx_seeta_theme/static/fonts/font-awesome/fonts/fontawesome-webfont.eot
sphinx_seeta_theme/static/fonts/font-awesome/fonts/fontawesome-webfont.svg
sphinx_seeta_theme/static/fonts/font-awesome/fonts/fontawesome-webfont.ttf
sphinx_seeta_theme/static/fonts/font-awesome/fonts/fontawesome-webfont.woff
sphinx_seeta_theme/static/fonts/font-awesome/fonts/fontawesome-webfont.woff2
sphinx_seeta_theme/static/fonts/font-en/css/font-en.css
sphinx_seeta_theme/static/fonts/font-en/fonts/CrimsonText-Bold.eot
sphinx_seeta_theme/static/fonts/font-en/fonts/CrimsonText-Bold.ttf
sphinx_seeta_theme/static/fonts/font-en/fonts/CrimsonText-Bold.woff
sphinx_seeta_theme/static/fonts/font-en/fonts/CrimsonText-Bold.woff2
sphinx_seeta_theme/static/fonts/font-en/fonts/CrimsonText-BoldItalic.eot
sphinx_seeta_theme/static/fonts/font-en/fonts/CrimsonText-BoldItalic.ttf
sphinx_seeta_theme/static/fonts/font-en/fonts/CrimsonText-BoldItalic.woff
sphinx_seeta_theme/static/fonts/font-en/fonts/CrimsonText-BoldItalic.woff2
sphinx_seeta_theme-0.1.1.dist-info/LICENSE
sphinx_seeta_theme-0.1.1.dist-info/METADATA
sphinx_seeta_theme-0.1.1.dist-info/WHEEL
sphinx_seeta_theme-0.1.1.dist-info/entry_points.txt
sphinx_seeta_theme-0.1.1.dist-info/top_level.txt
sphinx_seeta_theme-0.1.1.dist-info/RECORD
