Metadata-Version: 2.1
Name: sphinx-seeta-theme
Version: 0.1.1
Summary: Sphinx theme for seeta documentations.
Author: SeetaTech
License: BSD 2-Clause
Platform: UNKNOWN
Classifier: Framework :: Sphinx
Classifier: Framework :: Sphinx :: Theme
Classifier: Development Status :: 5 - Production/Stable
Classifier: License :: OSI Approved :: MIT License
Classifier: Environment :: Console
Classifier: Environment :: Web Environment
Classifier: Intended Audience :: Developers
Classifier: Programming Language :: Python :: 3
Classifier: Programming Language :: Python :: 3 :: Only
Classifier: Operating System :: OS Independent
Classifier: Topic :: Documentation
Classifier: Topic :: Software Development :: Documentation
License-File: LICENSE
Requires-Dist: sphinx (>=3.3.0)
Requires-Dist: commonmark
Requires-Dist: sphinxcontrib-katex
Requires-Dist: breathe
